znote/__init__.py
znote/client.py
znote/main.py
znote/server.py
znote/app/display.py
znote/app/input.py
znote/core/auth.py
znote/core/config.py
znote/core/editor.py
znote/core/gen.py
znote/core/pack.py
znote/core/structure.py
znote/core/workspace.py
znote/core/client/connect.py
znote/core/client/fetch.py
znote/core/client/metafile.py
znote/core/client/settings.py
znote/core/client/token.py
znote/core/server/note.py
znote/core/server/settings.py
znote/model/models.py
znote-1.6.1.dist-info/licenses/LICENSE
znote-1.6.1.dist-info/METADATA
znote-1.6.1.dist-info/WHEEL
znote-1.6.1.dist-info/entry_points.txt
znote-1.6.1.dist-info/top_level.txt
znote-1.6.1.dist-info/RECORD
