Metadata-Version: 2.4
Name: znote
Version: 1.6.1
Summary: Vault de prise de note
Author: 
License: mit
Platform: ALL
License-File: LICENSE
Requires-Dist: chardet
Requires-Dist: pyotp
Requires-Dist: pycryptodome
Requires-Dist: zpp_color
Requires-Dist: zpp_args
Requires-Dist: zpp_ManagedFile
Requires-Dist: prompt_toolkit
Requires-Dist: dill
Requires-Dist: impmagic
Requires-Dist: pyyaml
Requires-Dist: cryptography
Requires-Dist: sqlalchemy
Dynamic: description
Dynamic: description-content-type
Dynamic: keywords
Dynamic: license
Dynamic: license-file
Dynamic: platform
Dynamic: requires-dist
Dynamic: summary
